pyroofit/__init__.py
pyroofit/composites.py
pyroofit/data.py
pyroofit/models.py
pyroofit/observables.py
pyroofit/pdf.py
pyroofit/plotting.py
pyroofit/utilities.py
pyroofit-0.9.6.dist-info/AUTHORS.rst
pyroofit-0.9.6.dist-info/LICENSE.txt
pyroofit-0.9.6.dist-info/METADATA
pyroofit-0.9.6.dist-info/WHEEL
pyroofit-0.9.6.dist-info/entry_points.txt
pyroofit-0.9.6.dist-info/top_level.txt
pyroofit-0.9.6.dist-info/RECORD
