Metadata-Version: 2.1
Name: pyroofit
Version: 0.9.6
Summary: Python wrapper for RooFit to create fits easily with pandas DataFrames.
Home-page: http://www.desy.de/~swehle/pyroofit
Author: Simon Wehle
Author-email: simon.wehle@desy.de
License: mit
Platform: any
Classifier: Development Status :: 4 - Beta
Classifier: Programming Language :: Python
Requires-Dist: root-numpy
